{
  "requestsFinished": 101,
  "requestsFailed": 0,
  "requestsRetries": 18,
  "requestsFailedPerMinute": 0,
  "requestsFinishedPerMinute": 2,
  "requestMinDurationMillis": 19302,
  "requestMaxDurationMillis": 44690,
  "requestTotalFailedDurationMillis": 0,
  "requestTotalFinishedDurationMillis": 2599751,
  "crawlerStartedAt": "2026-02-17T11:15:19.906Z",
  "crawlerFinishedAt": null,
  "statsPersistedAt": "2026-02-17T11:59:20.137Z",
  "crawlerRuntimeMillis": 2640621,
  "crawlerLastStartTimestamp": 1771326919516,
  "requestRetryHistogram": [
    83,
    18
  ],
  "statsId": 0,
  "requestAvgFailedDurationMillis": null,
  "requestAvgFinishedDurationMillis": 25740,
  "requestTotalDurationMillis": 2599751,
  "requestsTotal": 101,
  "requestsWithStatusCode": {
    "200": 102,
    "403": 23
  },
  "errors": {},
  "retryErrors": {
    "/root/copychu-scraper/node_modules/@crawlee/basic/internals/basic-crawler.js:903:19": {
      "missing error code": {
        "Error": {
          "Request blocked - received 403 status code.": {
            "count": 23
          }
        }
      }
    }
  }
}