{
  "usableSessionsCount": 2,
  "retiredSessionsCount": 0,
  "sessions": [
    {
      "id": "session_hhkjIZT3Dq",
      "cookieJar": {
        "version": "tough-cookie@6.0.0",
        "storeType": "MemoryCookieStore",
        "rejectPublicSuffixes": true,
        "enableLooseMode": false,
        "allowSpecialUseDomain": true,
        "prefixSecurity": "silent",
        "cookies": []
      },
      "userData": {},
      "maxErrorScore": 3,
      "errorScoreDecrement": 0.5,
      "expiresAt": "2026-01-16T01:42:32.288Z",
      "createdAt": "2026-01-16T00:52:32.288Z",
      "usageCount": 0,
      "maxUsageCount": 50,
      "errorScore": 0
    },
    {
      "id": "session_ievffFOo5d",
      "cookieJar": {
        "version": "tough-cookie@6.0.0",
        "storeType": "MemoryCookieStore",
        "rejectPublicSuffixes": true,
        "enableLooseMode": false,
        "allowSpecialUseDomain": true,
        "prefixSecurity": "silent",
        "cookies": [
          {
            "key": "page_uid",
            "value": "jTE71dqo0qMDLt9EzAK-232943",
            "expires": "2026-01-16T01:42:38.199Z",
            "domain": "naver.com",
            "path": "/",
            "hostOnly": false,
            "creation": "2026-01-16T00:52:38.203Z",
            "lastAccessed": "2026-01-16T00:52:38.203Z"
          },
          {
            "key": "_naver_usersession_",
            "value": "cBOTHuMjbXyYBn5b56pQNW/b",
            "expires": "2026-01-16T00:57:37.450Z",
            "domain": "naver.com",
            "path": "/",
            "hostOnly": false,
            "creation": "2026-01-16T00:52:38.210Z",
            "lastAccessed": "2026-01-16T00:52:38.210Z"
          }
        ]
      },
      "userData": {},
      "maxErrorScore": 3,
      "errorScoreDecrement": 0.5,
      "expiresAt": "2026-01-16T01:42:32.291Z",
      "createdAt": "2026-01-16T00:52:32.291Z",
      "usageCount": 1,
      "maxUsageCount": 50,
      "errorScore": 0
    }
  ]
}