{
  "requestsFinished": 0,
  "requestsFailed": 0,
  "requestsRetries": 0,
  "requestsFailedPerMinute": 0,
  "requestsFinishedPerMinute": 0,
  "requestMinDurationMillis": null,
  "requestMaxDurationMillis": 0,
  "requestTotalFailedDurationMillis": 0,
  "requestTotalFinishedDurationMillis": 0,
  "crawlerStartedAt": "2026-02-08T09:02:21.398Z",
  "crawlerFinishedAt": "2026-02-08T09:02:21.420Z",
  "statsPersistedAt": "2026-02-08T09:02:21.420Z",
  "crawlerRuntimeMillis": 162,
  "crawlerLastStartTimestamp": 1770541341258,
  "requestRetryHistogram": [],
  "statsId": 2354,
  "requestAvgFailedDurationMillis": null,
  "requestAvgFinishedDurationMillis": null,
  "requestTotalDurationMillis": 0,
  "requestsTotal": 0,
  "requestsWithStatusCode": {},
  "errors": {},
  "retryErrors": {}
}