{
  "requestsFinished": 0,
  "requestsFailed": 0,
  "requestsRetries": 0,
  "requestsFailedPerMinute": 0,
  "requestsFinishedPerMinute": 0,
  "requestMinDurationMillis": null,
  "requestMaxDurationMillis": 0,
  "requestTotalFailedDurationMillis": 0,
  "requestTotalFinishedDurationMillis": 0,
  "crawlerStartedAt": "2026-02-08T08:37:59.053Z",
  "crawlerFinishedAt": "2026-02-08T08:37:59.092Z",
  "statsPersistedAt": "2026-02-08T08:37:59.092Z",
  "crawlerRuntimeMillis": 241,
  "crawlerLastStartTimestamp": 1770539878851,
  "requestRetryHistogram": [],
  "statsId": 2100,
  "requestAvgFailedDurationMillis": null,
  "requestAvgFinishedDurationMillis": null,
  "requestTotalDurationMillis": 0,
  "requestsTotal": 0,
  "requestsWithStatusCode": {},
  "errors": {},
  "retryErrors": {}
}