{
  "requestsFinished": 0,
  "requestsFailed": 0,
  "requestsRetries": 0,
  "requestsFailedPerMinute": 0,
  "requestsFinishedPerMinute": 0,
  "requestMinDurationMillis": null,
  "requestMaxDurationMillis": 0,
  "requestTotalFailedDurationMillis": 0,
  "requestTotalFinishedDurationMillis": 0,
  "crawlerStartedAt": "2026-02-08T07:49:02.727Z",
  "crawlerFinishedAt": "2026-02-08T07:49:02.761Z",
  "statsPersistedAt": "2026-02-08T07:49:02.761Z",
  "crawlerRuntimeMillis": 277,
  "crawlerLastStartTimestamp": 1770536942484,
  "requestRetryHistogram": [],
  "statsId": 1590,
  "requestAvgFailedDurationMillis": null,
  "requestAvgFinishedDurationMillis": null,
  "requestTotalDurationMillis": 0,
  "requestsTotal": 0,
  "requestsWithStatusCode": {},
  "errors": {},
  "retryErrors": {}
}