{
  "requestsFinished": 0,
  "requestsFailed": 0,
  "requestsRetries": 0,
  "requestsFailedPerMinute": 0,
  "requestsFinishedPerMinute": 0,
  "requestMinDurationMillis": null,
  "requestMaxDurationMillis": 0,
  "requestTotalFailedDurationMillis": 0,
  "requestTotalFinishedDurationMillis": 0,
  "crawlerStartedAt": "2026-02-08T08:23:46.380Z",
  "crawlerFinishedAt": "2026-02-08T08:23:46.420Z",
  "statsPersistedAt": "2026-02-08T08:23:46.420Z",
  "crawlerRuntimeMillis": 235,
  "crawlerLastStartTimestamp": 1770539026185,
  "requestRetryHistogram": [],
  "statsId": 1952,
  "requestAvgFailedDurationMillis": null,
  "requestAvgFinishedDurationMillis": null,
  "requestTotalDurationMillis": 0,
  "requestsTotal": 0,
  "requestsWithStatusCode": {},
  "errors": {},
  "retryErrors": {}
}