{
  "requestsFinished": 0,
  "requestsFailed": 0,
  "requestsRetries": 0,
  "requestsFailedPerMinute": 0,
  "requestsFinishedPerMinute": 0,
  "requestMinDurationMillis": null,
  "requestMaxDurationMillis": 0,
  "requestTotalFailedDurationMillis": 0,
  "requestTotalFinishedDurationMillis": 0,
  "crawlerStartedAt": "2026-02-08T05:37:57.983Z",
  "crawlerFinishedAt": "2026-02-08T05:37:58.015Z",
  "statsPersistedAt": "2026-02-08T05:37:58.015Z",
  "crawlerRuntimeMillis": 240,
  "crawlerLastStartTimestamp": 1770529077775,
  "requestRetryHistogram": [],
  "statsId": 227,
  "requestAvgFailedDurationMillis": null,
  "requestAvgFinishedDurationMillis": null,
  "requestTotalDurationMillis": 0,
  "requestsTotal": 0,
  "requestsWithStatusCode": {},
  "errors": {},
  "retryErrors": {}
}