{
	"id": "E6UJnkiPFukKRlW",
	"json": "{\"id\":\"E6UJnkiPFukKRlW\",\"url\":\"https://www.oliveyoung.co.kr/store/goods/getGoodsDetail.do?goodsNo=B000000233325\",\"uniqueKey\":\"https://www.oliveyoung.co.kr/store/goods/getGoodsDetail.do?goodsNo=B000000233325\",\"method\":\"GET\",\"noRetry\":false,\"retryCount\":0,\"errorMessages\":[],\"headers\":{},\"userData\":{\"product\":{\"Id\":140,\"CreatedAt\":\"2026-02-17 11:12:47+00:00\",\"UpdatedAt\":null,\"Title\":null,\"product_url\":\"https://www.oliveyoung.co.kr/store/goods/getGoodsDetail.do?goodsNo=B000000233325\",\"title_kr\":null,\"price_original\":null,\"price_discount\":null,\"image_urls\":null,\"description\":null,\"category\":null,\"scraped_at\":null,\"sku\":\"B000000233325\",\"title_en\":null,\"description_en\":null,\"screenshot\":null,\"product_images\":null},\"index\":139,\"missingFields\":{\"needsTitleKr\":true,\"needsTitleEn\":true,\"needsPriceOriginal\":true,\"needsPriceDiscount\":true,\"needsDescription\":true,\"needsDescriptionEn\":true,\"needsImages\":true,\"needsPageVisit\":true,\"isComplete\":false}}}",
	"method": "GET",
	"orderNo": 1771326919763,
	"retryCount": 0,
	"uniqueKey": "https://www.oliveyoung.co.kr/store/goods/getGoodsDetail.do?goodsNo=B000000233325",
	"url": "https://www.oliveyoung.co.kr/store/goods/getGoodsDetail.do?goodsNo=B000000233325"
}